README.txt
setup.py
gravatar/__init__.py
gravatar.egg-info/PKG-INFO
gravatar.egg-info/SOURCES.txt
gravatar.egg-info/dependency_links.txt
gravatar.egg-info/top_level.txt