Metadata-Version: 1.0
Name: gravatar
Version: 0.1
Summary: Gravatar generator. Includes all API parameters included in their documentation.
Home-page: http://github.com/jakevoytko/pyGravatar
Author: Jake Voytko
Author-email: jakevoytko@gmail.com
License: 2-clause BSD
Keywords: Gravatar web avatar uri
Platform: UNKNOWN
